ConfigHandler.py
FileHandler.py
JsonHandler.py
README.md
YamlHandler.py
app.py
app.spec
getValue.py
pyproject.toml
styles_config.ini
jyc-0.1.11.dist-info/METADATA
jyc-0.1.11.dist-info/WHEEL
jyc-0.1.11.dist-info/entry_points.txt
jyc-0.1.11.dist-info/RECORD
