Metadata-Version: 2.1
Name: jyc
Version: 0.1.11
Summary: A configuration file handling library supporting INI, JSON, and YAML formats
License: MIT
Author: yubo
Author-email: your.email@example.com
Requires-Python: >=3.7,<4.0
Classifier: License :: OSI Approved :: MIT License
Classifier: Programming Language :: Python :: 3
Classifier: Programming Language :: Python :: 3.7
Classifier: Programming Language :: Python :: 3.8
Classifier: Programming Language :: Python :: 3.9
Classifier: Programming Language :: Python :: 3.10
Classifier: Programming Language :: Python :: 3.11
Classifier: Programming Language :: Python :: 3.12
Classifier: Programming Language :: Python :: 3.13
Requires-Dist: configparser (>=5.3.0,<6.0.0)
Requires-Dist: pygments (>=2.1.8,<3.0.0)
Requires-Dist: pyyaml (>=6.0,<7.0)
